{
  "data": {
    "products": {
      "edges": [
        {
          "node": {
            "id": "UHJvZHVjdDo2MzQ=",
            "name": "Voluptates quod asperiores iure.",
            "pricing": {
              "priceRange": {
                "start": {
                  "gross": {
                    "amount": "64.73",
                    "currency": "CHF"
                  }
                },
                "stop": {
                  "gross": {
                    "amount": "64.73",
                    "currency": "CHF"
                  }
                }
              }
            },
            "producer": {
              "firstName": "Anna",
              "lastName": "Barbey"
            },
            "productType": {
              "id": "UHJvZHVjdFR5cGU6OTc="
            },
            "thumbnail": {
              "alt": "",
              "url": "http://localhost:8000/media/__sized__/products/DDLFOFZTKKkYbMdQ-thumbnail-500x500.png"
            },
            "variants": [
              {
                "id": "UHJvZHVjdFZhcmlhbnQ6MzI0Mw==",
                "isAvailable": true,
                "name": "55cm x 55cm",
                "stockQuantity": 153
              }
            ]
          }
        },
        {
          "node": {
            "id": "UHJvZHVjdDo2MzQ=",
            "name": "Voluptates quod asperiores iure.",
            "pricing": {
              "priceRange": {
                "start": {
                  "gross": {
                    "amount": "26.8",
                    "currency": "CHF"
                  }
                },
                "stop": {
                  "gross": {
                    "amount": "26.8",
                    "currency": "CHF"
                  }
                }
              }
            },
            "producer": {
              "firstName": "Anna",
              "lastName": "Barbey"
            },
            "productType": {
              "id": "UHJvZHVjdFR5cGU6OTc="
            },
            "thumbnail": {
              "alt": "",
              "url": "http://localhost:8000/media/__sized__/products/DDLFOFZTKKkYbMdQ-thumbnail-500x500.png"
            },
            "variants": [
              {
                "id": "UHJvZHVjdFZhcmlhbnQ6MzI0NA==",
                "isAvailable": true,
                "name": "55cm x 55cm",
                "stockQuantity": 30
              }
            ]
          }
        }
      ],
      "pageInfo": {
        "endCursor": "YXJyYXljb25uZWN0aW9uOjE=",
        "startCursor": "YXJyYXljb25uZWN0aW9uOjA="
      },
      "totalCount": 2
    }
  }
}
