{
  "data": {
    "product": {
      "conservation": {
        "mode": "à température ambiante",
        "until": "2020-08-25"
      },
      "description": "Consequatur harum est voluptatem autem sequi. Distinctio eius reiciendis quas ex eveniet rerum expedita. Facere molestias illo labore. Quod dignissimos quis ad non beatae vitae.",
      "id": "UHJvZHVjdDoxNTc5",
      "images": [
        {
          "alt": "",
          "url": "/media/products/bXptuqavouGmyClo.png"
        },
        {
          "alt": "",
          "url": "/media/products/LDvseZGMrDqYIOtM.png"
        },
        {
          "alt": "",
          "url": "/media/products/CuDnOCqachGrkllX.png"
        },
        {
          "alt": "",
          "url": "/media/products/FjHIKYMcTFleZwAZ.png"
        },
        {
          "alt": "",
          "url": "/media/products/nmvddVVQglQPmPIp.png"
        },
        {
          "alt": "",
          "url": "/media/products/ImNKavFoKvxGidhN.png"
        },
        {
          "alt": "",
          "url": "/media/products/urVpqzcQLIUaSHcG.png"
        },
        {
          "alt": "",
          "url": "/media/products/OLcdScLNRtXuzpsj.png"
        },
        {
          "alt": "",
          "url": "/media/products/ObIxVeXLDlZMtwrg.png"
        },
        {
          "alt": "",
          "url": "/media/products/EhvFUYmkKYchgIOI.png"
        }
      ],
      "margin": {
        "manager": {
          "start": {
            "gross": {
              "amount": 3.4,
              "currency": "CHF"
            },
            "net": {
              "amount": 3.1,
              "currency": "CHF"
            },
            "tax": {
              "amount": 0.25,
              "currency": "CHF"
            }
          },
          "stop": {
            "gross": {
              "amount": 5.75,
              "currency": "CHF"
            },
            "net": {
              "amount": 5.3,
              "currency": "CHF"
            },
            "tax": {
              "amount": 0.4,
              "currency": "CHF"
            }
          }
        },
        "rex": {
          "start": {
            "gross": {
              "amount": 3.4,
              "currency": "CHF"
            },
            "net": {
              "amount": 3.1,
              "currency": "CHF"
            },
            "tax": {
              "amount": 0.25,
              "currency": "CHF"
            }
          },
          "stop": {
            "gross": {
              "amount": 5.75,
              "currency": "CHF"
            },
            "net": {
              "amount": 5.3,
              "currency": "CHF"
            },
            "tax": {
              "amount": 0.4,
              "currency": "CHF"
            }
          }
        },
        "softozor": {
          "start": {
            "gross": {
              "amount": 3.4,
              "currency": "CHF"
            },
            "net": {
              "amount": 3.1,
              "currency": "CHF"
            },
            "tax": {
              "amount": 0.25,
              "currency": "CHF"
            }
          },
          "stop": {
            "gross": {
              "amount": 5.75,
              "currency": "CHF"
            },
            "net": {
              "amount": 5.3,
              "currency": "CHF"
            },
            "tax": {
              "amount": 0.4,
              "currency": "CHF"
            }
          }
        }
      },
      "name": "Voluptatibus doloremque.",
      "pricing": {
        "priceRange": {
          "start": {
            "gross": {
              "amount": 67.25,
              "currency": "CHF"
            },
            "net": {
              "amount": 65.1,
              "currency": "CHF"
            },
            "productTax": {
              "amount": 1.4,
              "currency": "CHF"
            },
            "serviceTax": {
              "amount": 0.7,
              "currency": "CHF"
            }
          },
          "stop": {
            "gross": {
              "amount": 114.2,
              "currency": "CHF"
            },
            "net": {
              "amount": 110.6,
              "currency": "CHF"
            },
            "productTax": {
              "amount": 2.35,
              "currency": "CHF"
            },
            "serviceTax": {
              "amount": 1.2,
              "currency": "CHF"
            }
          }
        }
      },
      "producer": {
        "address": {
          "city": "Chappuis",
          "country": "CH",
          "postalCode": "1407",
          "streetAddress1": "chemin Pierre Bourquin"
        },
        "description": "Accusamus saepe magnam voluptatibus. Voluptatum quos perspiciatis eius aut numquam.\nAmet explicabo nemo assumenda optio libero iure. Placeat similique vitae consectetur reprehenderit sit iusto.",
        "firstName": "Nicole",
        "id": "VXNlcjoxMDcy",
        "lastName": "Robadey"
      },
      "purchaseCost": {
        "start": {
          "amount": "57.15",
          "currency": "CHF"
        },
        "stop": {
          "amount": "97.05",
          "currency": "CHF"
        }
      },
      "variants": [
        {
          "costPrice": {
            "amount": "84.8",
            "currency": "CHF"
          },
          "id": "UHJvZHVjdFZhcmlhbnQ6NjMzMA==",
          "isAvailable": true,
          "margin": {
            "manager": {
              "gross": {
                "amount": 5.0,
                "currency": "CHF"
              },
              "net": {
                "amount": 4.65,
                "currency": "CHF"
              },
              "tax": {
                "amount": 0.35,
                "currency": "CHF"
              }
            },
            "rex": {
              "gross": {
                "amount": 5.0,
                "currency": "CHF"
              },
              "net": {
                "amount": 4.65,
                "currency": "CHF"
              },
              "tax": {
                "amount": 0.35,
                "currency": "CHF"
              }
            },
            "softozor": {
              "gross": {
                "amount": 5.0,
                "currency": "CHF"
              },
              "net": {
                "amount": 4.65,
                "currency": "CHF"
              },
              "tax": {
                "amount": 0.35,
                "currency": "CHF"
              }
            }
          },
          "name": "500g",
          "pricing": {
            "price": {
              "gross": {
                "amount": 99.8,
                "currency": "CHF"
              },
              "net": {
                "amount": 96.65,
                "currency": "CHF"
              },
              "productTax": {
                "amount": 2.05,
                "currency": "CHF"
              },
              "serviceTax": {
                "amount": 1.05,
                "currency": "CHF"
              }
            }
          },
          "stockQuantity": 375
        },
        {
          "costPrice": {
            "amount": "59.8",
            "currency": "CHF"
          },
          "id": "UHJvZHVjdFZhcmlhbnQ6NjMzMQ==",
          "isAvailable": true,
          "margin": {
            "manager": {
              "gross": {
                "amount": 3.55,
                "currency": "CHF"
              },
              "net": {
                "amount": 3.25,
                "currency": "CHF"
              },
              "tax": {
                "amount": 0.25,
                "currency": "CHF"
              }
            },
            "rex": {
              "gross": {
                "amount": 3.55,
                "currency": "CHF"
              },
              "net": {
                "amount": 3.25,
                "currency": "CHF"
              },
              "tax": {
                "amount": 0.25,
                "currency": "CHF"
              }
            },
            "softozor": {
              "gross": {
                "amount": 3.55,
                "currency": "CHF"
              },
              "net": {
                "amount": 3.25,
                "currency": "CHF"
              },
              "tax": {
                "amount": 0.25,
                "currency": "CHF"
              }
            }
          },
          "name": "1l",
          "pricing": {
            "price": {
              "gross": {
                "amount": 70.4,
                "currency": "CHF"
              },
              "net": {
                "amount": 68.15,
                "currency": "CHF"
              },
              "productTax": {
                "amount": 1.45,
                "currency": "CHF"
              },
              "serviceTax": {
                "amount": 0.75,
                "currency": "CHF"
              }
            }
          },
          "stockQuantity": 248
        },
        {
          "costPrice": {
            "amount": "57.15",
            "currency": "CHF"
          },
          "id": "UHJvZHVjdFZhcmlhbnQ6NjMzMg==",
          "isAvailable": true,
          "margin": {
            "manager": {
              "gross": {
                "amount": 3.4,
                "currency": "CHF"
              },
              "net": {
                "amount": 3.1,
                "currency": "CHF"
              },
              "tax": {
                "amount": 0.25,
                "currency": "CHF"
              }
            },
            "rex": {
              "gross": {
                "amount": 3.4,
                "currency": "CHF"
              },
              "net": {
                "amount": 3.1,
                "currency": "CHF"
              },
              "tax": {
                "amount": 0.25,
                "currency": "CHF"
              }
            },
            "softozor": {
              "gross": {
                "amount": 3.4,
                "currency": "CHF"
              },
              "net": {
                "amount": 3.1,
                "currency": "CHF"
              },
              "tax": {
                "amount": 0.25,
                "currency": "CHF"
              }
            }
          },
          "name": "1kg",
          "pricing": {
            "price": {
              "gross": {
                "amount": 67.25,
                "currency": "CHF"
              },
              "net": {
                "amount": 65.1,
                "currency": "CHF"
              },
              "productTax": {
                "amount": 1.4,
                "currency": "CHF"
              },
              "serviceTax": {
                "amount": 0.7,
                "currency": "CHF"
              }
            }
          },
          "stockQuantity": 350
        },
        {
          "costPrice": {
            "amount": "97.05",
            "currency": "CHF"
          },
          "id": "UHJvZHVjdFZhcmlhbnQ6NjMzMw==",
          "isAvailable": true,
          "margin": {
            "manager": {
              "gross": {
                "amount": 5.75,
                "currency": "CHF"
              },
              "net": {
                "amount": 5.3,
                "currency": "CHF"
              },
              "tax": {
                "amount": 0.4,
                "currency": "CHF"
              }
            },
            "rex": {
              "gross": {
                "amount": 5.75,
                "currency": "CHF"
              },
              "net": {
                "amount": 5.3,
                "currency": "CHF"
              },
              "tax": {
                "amount": 0.4,
                "currency": "CHF"
              }
            },
            "softozor": {
              "gross": {
                "amount": 5.75,
                "currency": "CHF"
              },
              "net": {
                "amount": 5.3,
                "currency": "CHF"
              },
              "tax": {
                "amount": 0.4,
                "currency": "CHF"
              }
            }
          },
          "name": "500g",
          "pricing": {
            "price": {
              "gross": {
                "amount": 114.2,
                "currency": "CHF"
              },
              "net": {
                "amount": 110.6,
                "currency": "CHF"
              },
              "productTax": {
                "amount": 2.35,
                "currency": "CHF"
              },
              "serviceTax": {
                "amount": 1.2,
                "currency": "CHF"
              }
            }
          },
          "stockQuantity": 249
        },
        {
          "costPrice": {
            "amount": "77.35",
            "currency": "CHF"
          },
          "id": "UHJvZHVjdFZhcmlhbnQ6NjMzNA==",
          "isAvailable": true,
          "margin": {
            "manager": {
              "gross": {
                "amount": 4.55,
                "currency": "CHF"
              },
              "net": {
                "amount": 4.2,
                "currency": "CHF"
              },
              "tax": {
                "amount": 0.35,
                "currency": "CHF"
              }
            },
            "rex": {
              "gross": {
                "amount": 4.55,
                "currency": "CHF"
              },
              "net": {
                "amount": 4.2,
                "currency": "CHF"
              },
              "tax": {
                "amount": 0.35,
                "currency": "CHF"
              }
            },
            "softozor": {
              "gross": {
                "amount": 4.55,
                "currency": "CHF"
              },
              "net": {
                "amount": 4.2,
                "currency": "CHF"
              },
              "tax": {
                "amount": 0.35,
                "currency": "CHF"
              }
            }
          },
          "name": "250ml",
          "pricing": {
            "price": {
              "gross": {
                "amount": 91.0,
                "currency": "CHF"
              },
              "net": {
                "amount": 88.15,
                "currency": "CHF"
              },
              "productTax": {
                "amount": 1.9,
                "currency": "CHF"
              },
              "serviceTax": {
                "amount": 1.0,
                "currency": "CHF"
              }
            }
          },
          "stockQuantity": 5
        }
      ]
    }
  }
}
