{
  "conservation": {
    "mode": "au frigo",
    "until": "2020-04-28T23:09:32+00:00"
  },
  "description": "Iusto natus dignissimos nihil. Architecto iusto aspernatur est. Voluptas dolorum soluta nulla quas facere.\nArchitecto exercitationem quos corrupti eos. Odit officiis fugit maiores.",
  "id": "UHJvZHVjdDoyNTI0",
  "images": [
    {
      "alt": "",
      "url": "products/KjYGlXXayFqTKOSZ.png"
    },
    {
      "alt": "",
      "url": "products/CosrTsiketAvquHH.png"
    },
    {
      "alt": "",
      "url": "products/oawCfFQTIwklOsVH.png"
    },
    {
      "alt": "",
      "url": "products/JIBfptIRyOTVuaFw.png"
    },
    {
      "alt": "",
      "url": "products/oLXDvBlqANvSaTRX.png"
    }
  ],
  "name": "Doloremque quis.",
  "pricing": {
    "priceRange": {
      "start": {
        "gross": {
          "amount": "56.09",
          "currency": "CHF"
        },
        "net": {
          "amount": "56.09",
          "currency": "CHF"
        },
        "tax": {
          "amount": 0,
          "currency": "CHF"
        }
      },
      "stop": {
        "gross": {
          "amount": "56.09",
          "currency": "CHF"
        },
        "net": {
          "amount": "56.09",
          "currency": "CHF"
        },
        "tax": {
          "amount": 0,
          "currency": "CHF"
        }
      }
    }
  },
  "producer": {
    "firstName": "Michel",
    "lastName": "Bernasconi"
  },
  "purchaseCost": {
    "start": {
      "amount": "56.09",
      "currency": "CHF"
    },
    "stop": {
      "amount": "56.09",
      "currency": "CHF"
    }
  },
  "variants": [
    {
      "costPrice": {
        "amount": "3.69",
        "currency": "CHF"
      },
      "id": "UHJvZHVjdFZhcmlhbnQ6MTI4MDc=",
      "isAvailable": true,
      "name": "5l",
      "pricing": {
        "price": {
          "gross": {
            "amount": "56.09",
            "currency": "CHF"
          },
          "net": {
            "amount": "56.09",
            "currency": "CHF"
          },
          "tax": {
            "amount": 0,
            "currency": "CHF"
          }
        }
      },
      "sku": "820482387",
      "stockQuantity": 239
    }
  ]
}
